autoflow/__init__.py
autoflow/defaults.py
autoflow/env.py
autoflow/main.py
autoflow/readme_template.py
autoflow/scripts/__init__.py
autoflow/scripts/git_connect.py
autoflow/scripts/mactab.py
autoflow/scripts/shell.py
autoflow/scripts/cli/__init__.py
autoflow/scripts/cli/jump.py
autoflow/scripts/cli/new.py
autoflow/scripts/cli/start.py
autoflow/scripts/create/__init__.py
autoflow/scripts/create/node.py
autoflow/scripts/create/python.py
autoflow/scripts/create/react.py
python_af-1.0.0.dist-info/LICENSE
python_af-1.0.0.dist-info/METADATA
python_af-1.0.0.dist-info/WHEEL
python_af-1.0.0.dist-info/entry_points.txt
python_af-1.0.0.dist-info/top_level.txt
python_af-1.0.0.dist-info/RECORD
