Metadata-Version: 2.1
Name: python-af
Version: 1.0.0
Summary: A python package that automates your workflow
Home-page: https://github.com/MLH-Fellowship/autoflow
Author: Team Autoflow
License: MIT
Keywords: autoflow,python-af,workflow automation,productivity
Platform: posix
Classifier: License :: OSI Approved :: MIT License
Classifier: Development Status :: 3 - Alpha
Classifier: Programming Language :: Python :: 3.8
Classifier: Operating System :: MacOS :: MacOS X
Classifier: Operating System :: POSIX :: Linux
Classifier: Topic :: Software Development :: Libraries :: Python Modules
Requires-Python: >=3.6
Requires-Dist: Click
Requires-Dist: PyGithub
Requires-Dist: gitpython
